doccle
