Metadata-Version: 2.1
Name: py-doccle
Version: 0.0.2
Summary: A Python package to get data from Doccle.
Home-page: https://github.com/sgilissen/py-doccle
Author: Steve Gilissen
License: GNU GPLv3
Classifier: Programming Language :: Python :: 3
Classifier: License :: OSI Approved :: GNU General Public License v3 (GPLv3)
Classifier: Programming Language :: Python :: 3.6
Classifier: Programming Language :: Python :: 3.7
Classifier: Programming Language :: Python :: 3.8
Classifier: Programming Language :: Python :: 3.9
Classifier: Programming Language :: Python :: 3.10
License-File: LICENSE.md
